{"docs_qunar环境使用_cms云开发.md":"DzgeV2m9","docs_qunar环境使用_md平台打包及手机debug包验证.md":"g6WteSsw","docs_qunar环境使用_rock组件迁移.md":"mkpQD2lT","docs_qunar环境使用_shark框架使用.md":"Bqlqh0c5","docs_ios_ios课程准备工作.md":"UExVlrTL","docs_qunar环境使用_qrn_切换线上环境和仿真环境.md":"-f2o2JTK","docs_html_h5form表单.md":"D-xAjQTX","docs_qunar环境使用_qrn_切换ab实验的代码.md":"U3TRYjb7","docs_android_搭建android环境.md":"nz4clHDq","docs_qunar环境使用_md平台下载debug包.md":"VSYEE7EC","docs_qunar环境使用_使用xcode模拟器调试qrn项目.md":"rix2XhRd","docs_ios_ios课程作业遇到的问题.md":"PMKb9oLm","docs_qunar环境使用_本地ide ssh连接云开发.md":"qZq4AQGU","docs_qunar环境使用_shark框架升级.md":"x_4AfaoO","docs_js_js事件循环(event loop).md":"o3g2Lb2b","docs_js_阻止冒泡事件，内外两层div都有点击事件，设置点击内层元素时不触发外层元素的点击事件.md":"x5dstIDG","docs_js_复制链接的api：clipboard.md":"lJEGSDlr","docs_js_js常用方法总结.md":"xlelvGdV","docs_qunar环境使用_portal平台打包.md":"7712ukjh","docs_python_操作数据库相关.md":"AkKzY8zr","docs_js_js __ 及隐式类型类型转换.md":"J6W1PbOH","docs_js_fetch函数.md":"iQTEcroC","docs_react native_animatrd动画使用.md":"CnYDzjc3","docs_react native_touchableopacity组件.md":"O6LZbUYZ","docs_react native_qunar框架知识点.md":"iU08nfuF","docs_nodejs_koa库使用.md":"FJIjBpna","docs_css_css总结.md":"3J6dRvcH","docs_react native_text组件.md":"Xll_D_ED","docs_css_伪类选择器实现：鼠标在悬浮按钮时弹出工具框.md":"j26t4did","docs_qunar环境使用_noah软路由环境使用.md":"CY7Cjv86","docs_js_cjs和mjs.md":"CyvIhkUY","docs_react native_react native总结.md":"9Boxvjg0","docs_qunar环境使用_灯塔平台mock数据.md":"lzQN685E","docs_qunar环境使用_rock项目启动.md":"yOZRm3_y","docs_react native_view组件.md":"-GzI9AGl","docs_css_before制作气泡框.md":"2-mDrht8","docs_react native_监听页面滚动：惯性滚动、拖拽滚动.md":"4eKLyPsC","docs_react native_创建qrn项目.md":"YmuMfdn8","docs_css_使用border属性绘制三角形.md":"379x0rrA","docs_git_git总结.md":"TlpkcWQF","docs_python_安装oss-sdk库.md":"c1FnoTfe","docs_js_eslint使用.md":"cuVHLmyr","docs_react native_qrn远程使用指南.md":"a9v2_WKd","docs_react_react框架解决跨域问题.md":"jXjoAyOk","docs_git_gitlab使用.md":"d84KbPYP","docs_css_伪类选择器：!hover.md":"_hQ4ctZC","docs_git_做项目的分支合并.md":"vh3-tG8t","docs_git_回退到指定版本.md":"tgJn-KlY","docs_js_js异步.md":"YKw7zzob","docs_机票售前客户端_flight_module_search工程_flight_module_search项目代码阅读.md":"XXdqy_yg","docs_机票售前客户端_home_rn工程_首页低价订阅卡片.md":"KuPn0xYS","docs_机票售前客户端_size分析.md":"EVCTURtF","docs_机票售前客户端_用户搜索航线达到阈值推荐订阅.md":"V6MSkAMU","docs_组件库_antd-select组件.md":"8Bqlvpuq","docs_机票售前客户端_接口整理.md":"Y7HJW0Pa","docs_知识_身份证最后一位校验码计算.md":"hdrZvw9x","docs_机票售前客户端_tarslib工程_发布新代码.md":"kS5v2iz8","docs_机票售前客户端_tarslib工程_本地调用从服务接口，达到调试目的.md":"4qr20aAn","docs_机票售前客户端_tarslib工程_环境、启动相关问题.md":"5GR_kA6E","docs_机票售前客户端_tarslib工程_连接主服务和从服务器.md":"F-fHBYYy","docs_机票售前客户端_flight_major_bundle工程_booking页_booking页返回ota页.md":"ug6tzeWj","docs_机票售前客户端_flight_major_bundle工程_代码阅读.md":"Lj8_iTPR","docs_机票售前客户端_flight_module_search工程_ota页_ota页.md":"2WEkd2R8","docs_机票售前客户端_flight_major_bundle工程_booking页_booking页总结.md":"FL9a8nyo","docs_机票售前客户端_flight_module_search工程_flightrow组件：机票列表中的每一项.md":"V6REvc1S","docs_分享_7.27组会.md.md":"oJJ8rxyT","docs_typescript_初使用.md":"mVTFWgea","docs_前端知识_logcat.md":"MozFZtgO","docs_前端知识_本地起项目，同一局域网内访问.md":"jRdzwXy4","docs_前端知识_跨域：cors.md":"_LAdaXpL","docs_外推系统3.0记录_cms外推3.0系统，启动职位详情页组件，获取不到职位信息.md":"SZKm7hRd","docs_外推系统3.0记录_cms外推3.0系统，分享出去的链接打开后，返回的是线上的内容，而不是自己开发的.md":"QEqKrPIF","docs_前端知识_代理.md":"Z44mOXVA","docs_外推系统3.0记录_cms项目启动后访问接口会重定向.md":"-dRl0WBc","docs_工具_charles代理yapi.md":"BefnAr6t","docs_工具_homebrew.md":"EeQ9yAvv","docs_工具_yapi.md":"Q8VavW8t","docs_工具_npm总结.md":"gthDLdcp","docs_react native_自定义组件_倒计时组件.md":"YEe4sSoU","docs_react_react生命周期.md":"PfAPv2HU","docs_react_setstate是同步还是异步.md":"C5M4EbPS","docs_react_虚拟dom和diff算法.md":"71457yx3","docs_react_总结.md":"6BIVlL8k","docs_react native_自定义组件_循环轮播组件.md":"QIVgwBJL","docs_react_mobx使用时，需要设置支持装饰器语法(@开头).md":"-rCk2h4f","docs_react_mobx总结.md":"I0pNp6Eq","docs_python_环境相关问题.md":"4fCOx4D9","docs_前端知识_linux下配置node环境.md":"WcHfWFDQ","docs_index.md":"4UCQ154O","docs_机票售前客户端_flight_module_search工程_ota页_ota页总结.md":"zllb0NwM","docs_组件库_antd-table组件.md":"GEDx5ift","docs_机票售前客户端_主库联调子库.md":"2_nFA1H9","docs_react_react _ ts _ vite构建项目的模版步骤.md":"jtFT3UQe","docs_待学.md":"y7ArXdcZ","docs_机票售前客户端_ tars-management-system工程_环境、启动相关问题.md":"TnTv3jXr","docs_组件库_antd总结.md":"gXzOX_wl","docs_知识_微信公众号.md":"4nT4mrmh","docs_前端知识_url schema.md":"LnlZgzhg","docs_工具_vscode相关.md":"FmV14mTi","docs_qunar环境使用_查问题.md":"QCIw-b3K","docs_工具_xcode相关.md":"QiNkDBdy","index.md":"Zvr4waC-","docs_工具_mac相关.md":"Cc85GKql"}
